pyswing/__init__.py
pyswing-0.0.1.dist-info/LICENSE
pyswing-0.0.1.dist-info/METADATA
pyswing-0.0.1.dist-info/WHEEL
pyswing-0.0.1.dist-info/top_level.txt
pyswing-0.0.1.dist-info/RECORD
